chess_gif/__init__.py
chess_gif/constants.py
chess_gif/create_frame.py
chess_gif/gif_maker.py
chess_gif/Images/.placeholder
chess_gif/data/pgn/MikelOjda_vs_iDontTalkiDoIt_2020.03.19.pgn
chess_gif/data/pgn/game_id_Vyx76Lee.json
chess_gif/data/pgn/game_id_YPRLLL4C.json
chess_gif/data/pgn/lichess_pgn_2020.08.01_Mrunank_vs_Blindtakes34.E2og9BtO.pgn
chess_gif/data/pgn/lichess_pgn_2020.08.01_Mrunank_vs_amaa18.Q2RJXD4T.pgn
chess_gif/data/pgn/lichess_pgn_2020.08.03_Mrunank_vs_prem_singh_bhati.gKZs5DjG.pgn
chess_gif/data/piece/alpha/bB.svg
chess_gif/data/piece/alpha/bH.svg
chess_gif/data/piece/alpha/bK.svg
chess_gif/data/piece/alpha/bN.svg
chess_gif/data/piece/alpha/bP.svg
chess_gif/data/piece/alpha/bQ.svg
chess_gif/data/piece/alpha/bR.svg
chess_gif/data/piece/alpha/wB.svg
chess_gif/data/piece/alpha/wH.svg
chess_gif/data/piece/alpha/wK.svg
chess_gif/data/piece/alpha/wN.svg
chess_gif/data/piece/alpha/wP.svg
chess_gif/data/piece/alpha/wQ.svg
chess_gif/data/piece/alpha/wR.svg
chess_gif/data/piece/california/bB.svg
chess_gif/data/piece/california/bK.svg
chess_gif/data/piece/california/bN.svg
chess_gif/data/piece/california/bP.svg
chess_gif/data/piece/california/bQ.svg
chess_gif/data/piece/california/bR.svg
chess_gif/data/piece/california/wB.svg
chess_gif/data/piece/california/wK.svg
chess_gif/data/piece/california/wN.svg
chess_gif/data/piece/california/wP.svg
chess_gif/data/piece/california/wQ.svg
chess_gif/data/piece/california/wR.svg
chess_gif/data/piece/cardinal/bB.svg
chess_gif/data/piece/cardinal/bK.svg
chess_gif/data/piece/cardinal/bN.svg
chess_gif/data/piece/cardinal/bP.svg
chess_gif/data/piece/cardinal/bQ.svg
chess_gif/data/piece/cardinal/bR.svg
chess_gif/data/piece/cardinal/wB.svg
chess_gif/data/piece/cardinal/wK.svg
chess_gif/data/piece/cardinal/wN.svg
chess_gif/data/piece/cardinal/wP.svg
chess_gif/data/piece/cardinal/wQ.svg
chess_gif/data/piece/cardinal/wR.svg
chess_gif/data/piece/cburnett/bB.svg
chess_gif/data/piece/cburnett/bK.svg
chess_gif-1.2.0.dist-info/LICENSE
chess_gif-1.2.0.dist-info/METADATA
chess_gif-1.2.0.dist-info/WHEEL
chess_gif-1.2.0.dist-info/top_level.txt
chess_gif-1.2.0.dist-info/RECORD
