Metadata-Version: 2.1
Name: chess_gif
Version: 1.2.0
Summary: A package for creating GIFs of chess game from PGN files.
Home-page: https://github.com/fork52/chess_gif
Author: Mrunank Mistry
Author-email: mrunankmistry52@gmail.com
Project-URL: Bug Tracker, https://github.com/fork52/chess_gif/issues
Classifier: Programming Language :: Python :: 3
Classifier: License :: OSI Approved :: MIT License
Classifier: Operating System :: OS Independent
Requires-Python: >=3.9
License-File: LICENSE
Requires-Dist: python-chess
Requires-Dist: pyvips
Requires-Dist: imageio
Requires-Dist: pygifsicle
Requires-Dist: Pillow
